{
  "project_info": {
    "project_number": "1070815829860",
    "project_id": "gastandoapp",
    "storage_bucket": "gastandoapp.appspot.com"
  },
  "client": [
    {
      "client_info": {
        "mobilesdk_app_id": "1:1070815829860:android:29d68f0ffddd865aed2471",
        "android_client_info": {
          "package_name": "com.example.gasteando"
        }
      },
      "oauth_client": [],
      "api_key": [
        {
          "current_key": "AIzaSyA5IuY3YEvAsXM-9VzUQJtVYt5xOaWgg04"
        }
      ],
      "services": {
        "appinvite_service": {
          "other_platform_oauth_client": []
        }
      }
    }
  ],
  "configuration_version": "1"
}